anicons.py
anicons-0.0.1.dist-info/METADATA
anicons-0.0.1.dist-info/WHEEL
anicons-0.0.1.dist-info/top_level.txt
anicons-0.0.1.dist-info/RECORD
