Metadata-Version: 2.1
Name: anicons
Version: 0.0.1
Summary: Anime icon creation tool!
Home-page: https://github.com/RobiMez/Anicons_py
Author: robimez
License: UNKNOWN
Platform: UNKNOWN
Classifier: Programming Language :: Python :: 3
Classifier: Programming Language :: Python :: 3.6
Classifier: Programming Language :: Python :: 3.7
Requires-Dist: jikanpy
Requires-Dist: pyfiglet
Requires-Dist: PyInquirer
Requires-Dist: PIL
